aws_utils/__init__.py
aws_utils/dynamodb.py
aws_utils/response.py
aws_utils/s3.py
aws_utils_for_lambda-1.0.3.dist-info/LICENSE
aws_utils_for_lambda-1.0.3.dist-info/METADATA
aws_utils_for_lambda-1.0.3.dist-info/WHEEL
aws_utils_for_lambda-1.0.3.dist-info/top_level.txt
aws_utils_for_lambda-1.0.3.dist-info/RECORD
