Metadata-Version: 2.1
Name: aws-utils-for-lambda
Version: 1.0.3
Summary: AWS utils for lambda
Home-page: https://github.com/nelsonsequiera/aws_utils_for_lambda
Author: Nelson Sequiera
Author-email: nelsonsequiera@gmail.com
License: UNKNOWN
Platform: UNKNOWN
Classifier: Programming Language :: Python :: 3.7
Classifier: Programming Language :: Python :: 2.7
Classifier: Operating System :: OS Independent
Classifier: Intended Audience :: Developers
Classifier: Natural Language :: English
Requires-Python: >=2.7
Requires-Dist: boto3 (==1.9.120)
